Pliki projektowe SCK/SCK_PROJ_SYNT2/MODEL/REGS.v
module REGS (
    input wire [3:0] i_reg0,
    input wire [3:0] i_reg1,
    input wire [3:0] i_reg2,
    input wire i_clk,
    input wire i_rsn,
    input wire signed [5:0] i_data2,
    output reg signed [5:0] o_data0,
    output reg signed [5:0] o_data1
);

    reg signed [5:0] RRR [1:11]; // Tablica rejestrów
    integer i; // Zmienna pomocnicza do pętli

    always @(posedge i_clk, negedge i_rsn) 
    begin
        if (!i_rsn) begin
            for(i = 1; i <= 11; i = i + 1)
                RRR[i] <= 0;
        end
        else begin
            if(i_reg2 != 0) 
                RRR[i_reg2] <= i_data2;
        end
    end

    always @(*)
    begin
        if(i_reg0 > 0 && i_reg0 <= 11)
            o_data0 = RRR[i_reg0];
        else 
            o_data0 = 0;
        if(i_reg1 > 0 && i_reg1 <= 11)
            o_data1 = RRR[i_reg1];
        else 
            o_data1 = 0;
    end

endmodule

Pliki projektowe SCK/SCK_PROJ_SYNT1/MODEL/ALU.v
module ALU (
    input signed [5:0] i_arg0,      // Pierwszy argument (ze znakiem)
    input signed [5:0] i_arg1,      // Drugi argument (ze znakiem)
    input [2:0] i_oper,             // Kod operacji (bez znaku)
    input [5:0] i_data,
    input i_imm,

    output reg signed [5:0] o_result, // Wynik operacji (ze znakiem)
    output reg [3:0] o_flag         // Flagi: [Positive, Zero, Negative, Overflow]
);
    reg signed [5:0] arg1;

    always @(*) begin
        // Domyślne wartości
        o_result = 6'b000000;

        if(i_imm == 1)
        begin
            arg1 = i_data;
        end

        else
        begin
            arg1 = i_arg1;
        end


        case (i_oper)
            3'b000: o_result = i_arg0 + arg1;       // Dodawania
            3'b001: o_result = i_arg0 - arg1;       // Odejmowanie
            3'b010: begin
                if (arg1 > 0)
                    o_result = i_arg0 << arg1;     // Przesunięcie bitowe
                else if (arg1 < 0)
                    o_result = i_arg0 >>> -arg1;
                else
                    o_result = i_arg0;   
            end          
            3'b011: o_result = i_arg0 & arg1;  // Iloczyn bitowy (AND)
            3'b100: o_result = i_arg0 | arg1;  // Suma bitowa (OR)
            3'b101: o_result = i_arg0 ^ arg1;  // Suma wyłączona (XOR)
            default: o_result = 0;          // Domyślnie 0
        endcase

        o_flag=4'b0000;
    if (o_result < 0) 
            o_flag[0] = 1;
    if (o_result > 0) 
            o_flag[1] = 1;
    if (o_result == 0) 
            o_flag[2] = 1;

    if (i_oper==3'b000)
        if ((i_arg0 > 0 && arg1 > 0 && o_result < 0) || (i_arg0 < 0 && arg1 < 0 && o_result > 0)) 
            o_flag[3] = 1; //overflow w dodawaniu występuje gdy a i b są dodatnie a suma ujemna,lub na odwrót

    if (i_oper==3'b001)
        if ((i_arg0 > 0 && arg1 < 0 && o_result < 0) || (i_arg0 < 0 && arg1 > 0 && o_result > 0)) 
            o_flag[3] = 1; //overflow w odejmowaniu występuje gdy a jest większe od zera a pozostałe są mniejsze, lub na odwrót


    end
endmodule

Pliki projektowe SCK/SCK_PROJ_2/MODEL/EXE.v
module EXE (i_oper, i_reg0, i_reg1, i_reg2, i_data2, i_data, i_imm, i_clk, i_rsn, o_flag, o_data);

    input wire [2:0] i_oper;
    input wire [3:0] i_reg0, i_reg1, i_reg2;
    input wire signed [5:0] i_data, i_data2;
    input wire i_imm;
    input wire i_clk;
    input wire i_rsn;

    output signed [5:0] o_data;
    output [3:0] o_flag;

    wire [5:0] data0;
    wire [5:0] data1;

    ALU u1 (.i_arg0(data0),
                .i_arg1(data1),
                .i_oper(i_oper),
                .i_data(i_data),
                .i_imm(i_imm),
                .o_result(o_data),
                .o_flag(o_flag));

    REGS u2 (.i_reg0(i_reg0),
                .i_reg1(i_reg1),
                .i_reg2(i_reg2),
                .i_data2(i_data2),
                .i_clk(i_clk),
                .i_rsn(i_rsn),
                .o_data0(data0),
                .o_data1(data1));

endmodule

Pliki projektowe SCK/SCK_PROJ_2/TESTBENCH/EXE_tb.v
`timescale 1ns/1ps


module EXE_tb;
    integer i;
    reg signed [5:0] i_data, i_data2;
    reg [2:0] i_oper;
    wire [3:0] o_flag;
    wire signed [5:0] o_data;
    reg i_clk;
    reg i_rsn, i_imm;
    reg [3:0] i_reg0, i_reg1, i_reg2;

    EXE exe1(
        .i_oper(i_oper),
        .i_reg0(i_reg0),
        .i_reg1(i_reg1),
        .i_reg2(i_reg2),
        .i_data(i_data),
        .i_imm(i_imm),
        .i_clk(i_clk),
        .i_rsn(i_rsn),
        .o_flag(o_flag),
        .o_data(o_data),
        .i_data2(o_data)
    );

    initial i_clk = 0;
    always #0.5 i_clk = ~i_clk; 


    initial begin
        
        i<=0;
        i_rsn<=1;
        i_imm <= 1'b1;
        i_oper <= 3'b0;
        i_reg0 <= 6'd0;

        for(i = 1; i <= 11; i = i + 1)
        begin
            i_data = 3;
            i_reg2 = i;
            #1;
        end

        i_reg2 = 0;
        i_imm = 0;

        ///////////

        // Inicjalizacja sygnałów
        i_rsn = 0; // Aktywacja resetu
        i_oper = 0;
        i_reg0 = 0;
        i_reg1 = 0;
        i_reg2 = 0;
        i_data = 0;
        i_data2 = 0;
        i_imm = 0;

        // Reset rejestrów
        #10 i_rsn = 1; // Dezaktywacja resetu

        // Wpisanie liczby 2 do pierwszego rejestru (i_reg2 = 1)
        @(posedge i_clk)
            i_imm = 1;
            i_oper = 3'b000;
            i_reg2 = 1;
            i_data = 2;
        #10;

        // Wpisanie liczby 5 do drugiego rejestru (i_reg2 = 2)
        @(posedge i_clk)
            i_imm = 1;
            i_oper = 3'b000;
            i_reg2 = 4'd2;
            i_data = 6'd5;
        #10;

        // Wykonanie operacji dodawania: suma rejestrów 1 i 2 -> zapis w rejestrze 3
        @(posedge i_clk)
            i_imm = 0;
            i_reg0 = 4'b0001;
            i_reg1 = 4'b0010;
            i_reg2 = 4'd3;
            i_oper = 3'b000;
        #10;

        //Odejmowanie
        @(posedge i_clk)
            i_imm = 0;
            i_reg0 = 4'b0010;
            i_reg1 = 4'b0011;
            i_reg2 = 4'd4;
            i_oper = 3'b001;
        #10;
        
        //Przesunięcie bitowe
        @(posedge i_clk)
            i_imm = 0;
            i_reg0 = 4'd2;
            i_reg1 = 4'd1;
            i_reg2 = 4'd5;
            i_oper = 3'b010;
        #10;

        //Przesunięcie bitowe w drugą
        @(posedge i_clk)
            i_imm = 0;
            i_reg0 = 4'd5;
            i_reg1 = 4'd4;
            i_reg2 = 4'd6;
            i_oper = 3'b010;
        #10;

        //AND
        @(posedge i_clk)
            i_imm = 0;
            i_reg0 = 4'd5;
            i_reg1 = 4'd3;
            i_reg2 = 4'd7;
            i_oper = 3'b011;
        #10;

        //OR
        @(posedge i_clk)
            i_imm = 0;
            i_reg0 = 4'd5;
            i_reg1 = 4'd1;
            i_reg2 = 4'd8;
            i_oper = 3'b100;
        #10;

        //Iloczyn bitowy
        @(posedge i_clk)
            i_imm = 0;
            i_reg0 = 4'd7;
            i_reg1 = 4'd8;
            i_reg2 = 4'd9;
            i_oper = 3'b101;
        #10;

         // Zakończenie symulacji po ostatnim teście
        #10 $finish;
    end


endmodule

Pliki projektowe SCK/SCK_PROJ_2/WORK/symulacja.vcd
$date
    Dec  5, 2024  11:13:43
$end
$version
    TOOL:	xmsim(64)	23.03-s007
$end
$timescale
    1 ps
$end

$scope module EXE_tb $end
$var integer  32 !    i $end
$var reg       6 "    i_data [5:0] $end
$var reg       6 #    i_data2 [5:0] $end
$var reg       3 $    i_oper [2:0] $end
$var wire      4 %    o_flag [3:0] $end
$var wire      6 &    o_data [5:0] $end
$var reg       1 '    i_clk $end
$var reg       1 (    i_rsn $end
$var reg       1 )    i_imm $end
$var reg       4 *    i_reg0 [3:0] $end
$var reg       4 +    i_reg1 [3:0] $end
$var reg       4 ,    i_reg2 [3:0] $end

$scope module exe1 $end
$var wire      3 -    i_oper [2:0] $end
$var wire      4 .    i_reg0 [3:0] $end
$var wire      4 /    i_reg1 [3:0] $end
$var wire      4 0    i_reg2 [3:0] $end
$var wire      6 1    i_data [5:0] $end
$var wire      6 2    i_data2 [5:0] $end
$var wire      1 3    i_imm  $end
$var wire      1 4    i_clk  $end
$var wire      1 5    i_rsn  $end
$var wire      6 &    o_data [5:0] $end
$var wire      4 %    o_flag [3:0] $end
$var wire      6 6    data0 [5:0] $end
$var wire      6 7    data1 [5:0] $end

$scope module u1 $end
$var wire      6 6    i_arg0 [5:0] $end
$var wire      6 7    i_arg1 [5:0] $end
$var wire      3 -    i_oper [2:0] $end
$var wire      6 1    i_data [5:0] $end
$var wire      1 3    i_imm  $end
$var reg       6 8    o_result [5:0] $end
$var reg       4 9    o_flag [3:0] $end
$var reg       6 :    arg1 [5:0] $end
$upscope $end


$scope module u2 $end
$var wire      4 .    i_reg0 [3:0] $end
$var wire      4 /    i_reg1 [3:0] $end
$var wire      4 0    i_reg2 [3:0] $end
$var wire      1 4    i_clk  $end
$var wire      1 5    i_rsn  $end
$var wire      6 2    i_data2 [5:0] $end
$var reg       6 ;    o_data0 [5:0] $end
$var reg       6 <    o_data1 [5:0] $end
$var reg       6 =    RRR[1] [5:0] $end
$var reg       6 >    RRR[2] [5:0] $end
$var reg       6 ?    RRR[3] [5:0] $end
$var reg       6 @    RRR[4] [5:0] $end
$var reg       6 A    RRR[5] [5:0] $end
$var reg       6 B    RRR[6] [5:0] $end
$var reg       6 C    RRR[7] [5:0] $end
$var reg       6 D    RRR[8] [5:0] $end
$var reg       6 E    RRR[9] [5:0] $end
$var reg       6 F    RRR[10] [5:0] $end
$var reg       6 G    RRR[11] [5:0] $end
$var integer  32 H    i $end
$upscope $end

$upscope $end

$upscope $end

$enddefinitions $end
$dumpvars
b0 !
b0 "
b0 #
b0 $
b100 %
b0 &
0'
1(
0)
b0 *
b0 +
b1 ,
b0 -
b0 .
b0 /
b1 0
b0 1
b0 2
03
04
15
b0 6
b0 7
b0 8
b100 9
b0 :
b0 ;
b0 <
bx =
bx >
bx ?
bx @
bx A
bx B
bx C
bx D
bx E
bx F
bx G
bx H
$end
#500
1'
b1 !
14
b0 ,
b11 *
b1 +
b0 =
b1 /
b11 .
b0 0
bx ;
bx 6
bx 8
b0 9
b0 %
bx &
#1000
0'
04
#1500
1'
b10 !
14
b1 ,
b1 0
#2000
0'
04
#2500
1'
b11 !
14
b10 ,
b10 0
#3000
0'
04
#3500
1'
b100 !
14
b11 ,
b0 >
b11 0
#4000
0'
04
#4500
1'
b101 !
14
b100 ,
b0 ?
b100 0
b0 ;
b0 6
b0 8
b0 &
b100 9
b100 %
#5000
0'
04
#5500
1'
b110 !
14
b101 ,
b0 @
b101 0
#6000
0'
04
#6500
1'
b111 !
14
b110 ,
b0 A
b110 0
#7000
0'
04
#7500
1'
b1000 !
14
b111 ,
b0 B
b111 0
#8000
0'
04
#8500
1'
b1001 !
14
b1000 ,
b0 C
b1000 0
#9000
0'
04
#9500
1'
b1010 !
14
b1001 ,
b0 D
b1001 0
#10000
0'
04
#10500
1'
b1011 !
14
b1010 ,
b0 E
b1010 0
#11000
0'
04
#11500
1'
b1100 !
14
b1011 ,
b0 F
b1011 0
#12000
0'
04
#12500
1'
14
b0 G
